auto_pytest_mg/__init__.py
auto_pytest_mg/__main__.py
auto_pytest_mg/args.py
auto_pytest_mg/cli.py
auto_pytest_mg/console.py
auto_pytest_mg/static.py
auto_pytest_mg/test_models/__init__.py
auto_pytest_mg/test_models/class_base.py
auto_pytest_mg/test_models/class_fixture.py
auto_pytest_mg/test_models/class_test_cases.py
auto_pytest_mg/test_models/function_test_case.py
auto_pytest_mg/test_models/import_fixtures.py
auto_pytest_mg/test_models/test_file.py
auto_pytest_mg/utils.py
auto_pytest_mg-0.8.0.dist-info/entry_points.txt
auto_pytest_mg-0.8.0.dist-info/LICENSE
auto_pytest_mg-0.8.0.dist-info/WHEEL
auto_pytest_mg-0.8.0.dist-info/METADATA
auto_pytest_mg-0.8.0.dist-info/RECORD
