Metadata-Version: 2.1
Name: auto-pytest-mg
Version: 0.8.0
Summary: Awesome `auto_pytest_mg` is a Python cli/package created with https://github.com/TezRomacH/python-package-template
Home-page: https://github.com/auto_pytest_mg/auto_pytest_mg
License: MIT
Author: auto_pytest_mg
Author-email: ryan.ozelie@gmail.com
Requires-Python: >=3.7,<4.0
Classifier: Development Status :: 3 - Alpha
Classifier: Intended Audience :: Developers
Classifier: License :: OSI Approved :: MIT License
Classifier: Operating System :: OS Independent
Classifier: Programming Language :: Python :: 3
Classifier: Programming Language :: Python :: 3.10
Classifier: Programming Language :: Python :: 3.7
Classifier: Programming Language :: Python :: 3.8
Classifier: Programming Language :: Python :: 3.9
Classifier: Topic :: Software Development :: Libraries :: Python Modules
Requires-Dist: importlib_metadata (>=4.5.0,<5.0.0); python_version < "3.8"
Requires-Dist: inflection (>=0.5.1,<0.6.0)
Requires-Dist: isort (>=5.10.1,<6.0.0)
Requires-Dist: rich (>=12.4.4,<13.0.0)
Requires-Dist: typer[all] (>=0.4.0,<0.5.0)
Project-URL: Repository, https://github.com/auto_pytest_mg/auto_pytest_mg
